<?xml version="1.0" encoding="utf-8" ?>
<xml>
  <Level name ="Level 3" stages="12">
    <Stage x="0" y="0" w="f" h="f">
      <Start x="f-60" y="f-75" boundary="right"/>
      <Static type ="left_wall" x="0" y="0" w="10" h="f-100" collide ="true"/>
      <Static type ="floor" x="0" y="f-10" w="40" h="40" collide ="true"/>
      <Static type ="floor" x="f-50" y="f-10" w="f" h="40" collide ="true"/>
      <Static type ="right_wall" x="f-10" y="0" w="10" h="f-100" collide="true"/>
      <Static type ="ceiling" x="0" y="0" w="f" h="10" collide="true"/>
      <Platform x="c-40" y="c+200" w="60" h="25" distance ="255" speed ="2" direction="true"/>
      <Static type ="platform" x="160" y="c+175" w="60" h="25" collide ="true"/>
      <Static type ="platform" x="c-50" y="c+175" w="60" h="25" collide ="true"/>
      <Static type ="platform" x="c+160" y="c+175" w="60" h="25" collide ="true"/>
      <Static type ="spikes-H" x="45" y="f-25" w="110" h="25" collide ="false"/>
      <Static type ="spikes-H" x="155" y="f-25" w="100" h="25" collide ="false"/>
      <Static type ="spikes-H" x="255" y="f-25" w="100" h="25" collide ="false"/>
      <Static type ="spikes-H" x="355" y="f-25" w="100" h="25" collide ="false"/>
      <Static type ="spikes-H" x="455" y="f-25" w="100" h="25" collide ="false"/>
      <Static type ="spikes-H" x="555" y="f-25" w="100" h="25" collide ="false"/>
      <Static type ="spikes-H" x="655" y="f-25" w="100" h="25" collide ="false"/>
      <LightEffect effect="circle" x="113" y="c-18" w="150" h="150" color="FFFF00"/>
      <AnimatedStatic type="flames" x="175" y="c-185" w="30" h="260" collide="false" width="30" speed="0.05"/>
      <LightEffect effect="circle" x="539" y="c-18" w="150" h="150" color="FFFF00"/>
      <AnimatedStatic type="flames" x="602" y="c-185" w="30" h="260" collide="false" width="30" speed="0.05"/>
      <Background type="ParkingLot"/>
      <End x="60" y="f-75" boundary="left"/>
    </Stage>
  </Level>
</xml>